{"cameraMode":{"drawMode":0,"name":"Shaded","section":"Shading Mode"},"sceneLighting":false,"audioPlay":false,"sceneViewState":{"m_AlwaysRefresh":false,"showFog":true,"showSkybox":false,"showFlares":true,"showImageEffects":true,"showParticleSystems":true,"showVisualEffectGraphs":true,"m_FxEnabled":true},"in2DMode":false,"pivot":{"x":0.0,"y":1.9500000476837159,"z":12.970000267028809},"rotation":{"x":-0.0004587446164805442,"y":-0.9983617067337036,"z":-0.05666957050561905,"w":0.00808329600840807},"size":3.024744987487793,"orthographic":false}